README.md
setup.py
adttools/__init__.py
adttools.egg-info/PKG-INFO
adttools.egg-info/SOURCES.txt
adttools.egg-info/dependency_links.txt
adttools.egg-info/requires.txt
adttools.egg-info/top_level.txt
adttools/helper/DeployHelper.py
adttools/helper/ModelHelper.py
adttools/helper/PropertyHelper.py
adttools/helper/QueryHelper.py
adttools/helper/RelationshipHelper.py
adttools/helper/RequestHelper.py
adttools/helper/TwinHelper.py
adttools/helper/__init__.py