Metadata-Version: 2.1
Name: adttools
Version: 1.0.1
Summary: Toolkit for calling Azure digital twins REST API.
Home-page: https://github.com/kent010341/azure-digital-twins-tools
Author: kent010341
Author-email: kent010341@gmail.com
License: UNKNOWN
Keywords: adt,azure,digital twins
Platform: UNKNOWN
Classifier: Development Status :: 5 - Production/Stable
Classifier: Intended Audience :: Developers
Classifier: Programming Language :: Python :: 3
Classifier: License :: OSI Approved :: MIT License
Classifier: Operating System :: OS Independent
Requires-Python: >=3.6
